eventual_tortoise/__init__.py
eventual_tortoise/event_schedule.py
eventual_tortoise/integrity_guard.py
eventual_tortoise/mixin.py
eventual_tortoise/relation.py
eventual_tortoise/repository.py
eventual_tortoise/work_unit.py
eventual_tortoise-0.5.0.dist-info/WHEEL
eventual_tortoise-0.5.0.dist-info/METADATA
eventual_tortoise-0.5.0.dist-info/RECORD
