Metadata-Version: 2.1
Name: eventual-tortoise
Version: 0.5.0
Summary: 
Author: Ivan Dmitriesvkii
Author-email: ivan.dmitrievsky@gmail.com
Requires-Python: >=3.7,<4.0
Classifier: Programming Language :: Python :: 3
Classifier: Programming Language :: Python :: 3.7
Classifier: Programming Language :: Python :: 3.8
Classifier: Programming Language :: Python :: 3.9
Requires-Dist: eventual (>=0,<1)
Requires-Dist: orjson (>=3.5.2,<4.0.0)
Requires-Dist: tortoise-orm (>=0.17.2,<0.18.0)
